<?xml version="1.0" encoding="windows-1252" ?>
<!DOCTYPE ViewObject SYSTEM "jbo_03_01.dtd">
<!---->
<ViewObject
  xmlns="http://xmlns.oracle.com/bc4j"
  Name="SysGeneralValueVO"
  Version="12.1.3.10.47"
  InheritPersonalization="merge"
  SelectListFlags="1"
  FromListFlags="1"
  WhereFlags="1"
  BindingStyle="JDBC"
  CustomQuery="false"
  SelectAllAttributes="false"
  PageIterMode="Full">
  <Variable
    Name="P_ADF_VALUE_SET_ID"
    Kind="viewcriteria"
    Type="java.lang.Integer"/>
  <EntityUsage
    Name="SysGeneralValue"
    Entity="erpadm.modeladm.admeo.SysGeneralValue"/>
  <ViewAttribute
    Name="ValueId"
    IsNotNull="true"
    PrecisionRule="true"
    EntityAttrName="ValueId"
    EntityUsage="SysGeneralValue"
    AliasName="VALUE_ID"/>
  <ViewAttribute
    Name="ValueDescription"
    PrecisionRule="true"
    EntityAttrName="ValueDescription"
    EntityUsage="SysGeneralValue"
    AliasName="VALUE_DESCRIPTION"/>
  <ViewAttribute
    Name="ValueSetId"
    PrecisionRule="true"
    EntityAttrName="ValueSetId"
    EntityUsage="SysGeneralValue"
    AliasName="VALUE_SET_ID"/>
  <ViewAttribute
    Name="CreatedBy"
    PrecisionRule="true"
    EntityAttrName="CreatedBy"
    EntityUsage="SysGeneralValue"
    AliasName="CREATED_BY"/>
  <ViewAttribute
    Name="CreatedDate"
    PrecisionRule="true"
    EntityAttrName="CreatedDate"
    EntityUsage="SysGeneralValue"
    AliasName="CREATED_DATE"/>
  <ViewAttribute
    Name="LastUpdatedBy"
    PrecisionRule="true"
    EntityAttrName="LastUpdatedBy"
    EntityUsage="SysGeneralValue"
    AliasName="LAST_UPDATED_BY"/>
  <ViewAttribute
    Name="LastUpdatedDate"
    PrecisionRule="true"
    EntityAttrName="LastUpdatedDate"
    EntityUsage="SysGeneralValue"
    AliasName="LAST_UPDATED_DATE"/>
  <ViewAttribute
    Name="ValueCode"
    PrecisionRule="true"
    EntityAttrName="ValueCode"
    EntityUsage="SysGeneralValue"
    AliasName="VALUE_CODE"/>
  <ViewAttribute
    Name="IsActive"
    PrecisionRule="true"
    EntityAttrName="IsActive"
    EntityUsage="SysGeneralValue"
    AliasName="IS_ACTIVE"/>
  <ViewCriteria
    Name="SysGeneralValueByValueSetIDVC"
    ViewObjectName="erpadm.modeladm.admvo.SysGeneralValueVO"
    Conjunction="AND">
    <Properties>
      <CustomProperties>
        <Property
          Name="displayOperators"
          Value="InAdvancedMode"/>
        <Property
          Name="autoExecute"
          Value="false"/>
        <Property
          Name="allowConjunctionOverride"
          Value="true"/>
        <Property
          Name="showInList"
          Value="true"/>
        <Property
          Name="mode"
          Value="Basic"/>
      </CustomProperties>
    </Properties>
    <ViewCriteriaRow
      Name="SysGeneralValueVOCriteria_row_0"
      UpperColumns="1">
      <ViewCriteriaItem
        Name="ValueSetId"
        ViewAttribute="ValueSetId"
        Operator="="
        Conjunction="AND"
        Value=":P_ADF_VALUE_SET_ID"
        IsBindVarValue="true"
        Required="Optional"/>
    </ViewCriteriaRow>
  </ViewCriteria>
  <ViewCriteria
    Name="SysGeneralValueActiveVC"
    ViewObjectName="erpadm.modeladm.admvo.SysGeneralValueVO"
    Conjunction="AND">
    <Properties>
      <CustomProperties>
        <Property
          Name="displayOperators"
          Value="InAdvancedMode"/>
        <Property
          Name="autoExecute"
          Value="false"/>
        <Property
          Name="allowConjunctionOverride"
          Value="true"/>
        <Property
          Name="showInList"
          Value="true"/>
        <Property
          Name="mode"
          Value="Basic"/>
      </CustomProperties>
    </Properties>
    <ViewCriteriaRow
      Name="SysGeneralValueVOCriteria_row_0"
      UpperColumns="1">
      <ViewCriteriaItem
        Name="IsActive"
        ViewAttribute="IsActive"
        Operator="="
        Conjunction="AND"
        Value="Y"
        UpperColumns="0"
        Required="Optional"/>
    </ViewCriteriaRow>
  </ViewCriteria>
  <SortCriteria>
    <Sort
      Attribute="ValueId"/>
  </SortCriteria>
</ViewObject>
